cuddle/__init__.py
cuddle/_escaping.py
cuddle/decoder.py
cuddle/encoder.py
cuddle/exception.py
cuddle/grammar.py
cuddle/grammar.tatsu
cuddle/py.typed
cuddle/structure.py
cuddle-1.0.6.dist-info/LICENSE.txt
cuddle-1.0.6.dist-info/WHEEL
cuddle-1.0.6.dist-info/METADATA
cuddle-1.0.6.dist-info/RECORD
