Metadata-Version: 2.1
Name: cuddle
Version: 1.0.6
Summary: A Python library for the KDL Document Language.
Home-page: https://github.com/djmattyg007/python-cuddle
License: MIT
Author: Matthew Gamble
Author-email: git@matthewgamble.net
Requires-Python: >=3.9,<4.0
Classifier: Development Status :: 5 - Production/Stable
Classifier: Intended Audience :: Developers
Classifier: License :: OSI Approved :: MIT License
Classifier: Operating System :: OS Independent
Classifier: Programming Language :: Python :: 3
Classifier: Programming Language :: Python :: 3.10
Classifier: Programming Language :: Python :: 3.9
Requires-Dist: regex (>=2021.8.28,<2022.0.0)
Requires-Dist: tatsu (>=5.6.1,<6.0.0)
Project-URL: Issues, https://github.com/djmattyg007/python-cuddle/issues
Project-URL: Repository, https://github.com/djmattyg007/python-cuddle
Project-URL: Source, https://github.com/djmattyg007/python-cuddle
